<?xml version='1.0' encoding='UTF-8'?>
<widget xmlns = "http://www.w3.org/ns/widgets"
		xmlns:gap = "http://phonegap.com/ns/1.0"
		id = "org.wjbz82.hackillinois"
		versionCode = "10"
		version = "1.1.0">

	<name>Test Application</name>

	<description>
		A simple test to get familiar with phoneGap
	</description>

	<author href='#' email='wjbz82@mail.missouri.edu'>
		William Boening
	</author>

	<feature name="http://api.phonegap.com/1.0/camera"/>
    <feature name="http://api.phonegap.com/1.0/contacts"/>
    <feature name="http://api.phonegap.com/1.0/file"/>
    <feature name="http://api.phonegap.com/1.0/geolocation"/>
    <feature name="http://api.phonegap.com/1.0/media"/>
    <feature name="http://api.phonegap.com/1.0/network"/>
    <feature name="http://api.phonegap.com/1.0/notification"/>
 
</widget>